{
    "rank":{
        "0":1,
        "1":2,
        "2":3,
        "3":4,
        "4":5,
        "5":6,
        "6":7,
        "7":8,
        "8":9,
        "9":10,
        "10":11,
        "11":12,
        "12":13
    },
    "entry_name":{
        "0":"RojakkingFC",
        "1":"Gunners fc",
        "2":"LPT fighter",
        "3":"bukanSalahku",
        "4":"V.Gyokeres fc",
        "5":"Nippon Taqara",
        "6":"Goyangdek",
        "7":"Boboiboy Gentar",
        "8":"KuiFutball",
        "9":"BetrayerFC",
        "10":"Cem Fc",
        "11":"Laksamana FC",
        "12":"Yakkyakkyeah"
    },
    "player_name":{
        "0":"Mohd Shahzani Ali",
        "1":"dukun zai",
        "2":"Lantoi Bkc",
        "3":"Zarif Zakwan",
        "4":"ozool ismail",
        "5":"Muhamad Syahir Abu Bakar",
        "6":"Master Finger",
        "7":"Hafiz Ismail",
        "8":"Kuwie Mans",
        "9":"Han Takiya",
        "10":"Rasyid Razak",
        "11":"Laksamana Football Club",
        "12":"Ike Singge"
    },
    "event_total":{
        "0":45,
        "1":39,
        "2":38,
        "3":37,
        "4":36,
        "5":36,
        "6":34,
        "7":32,
        "8":29,
        "9":29,
        "10":28,
        "11":25,
        "12":24
    }
}