{
    "rank":{
        "0":1,
        "1":2,
        "2":3,
        "3":4,
        "4":5,
        "5":6,
        "6":7,
        "7":8,
        "8":9,
        "9":10,
        "10":11,
        "11":12,
        "12":13
    },
    "entry_name":{
        "0":"bukanSalahku",
        "1":"Nippon Taqara",
        "2":"Cem Fc",
        "3":"RojakkingFC",
        "4":"LPT fighter",
        "5":"Boboiboy Gentar",
        "6":"Yakkyakkyeah",
        "7":"Goyangdek",
        "8":"Laksamana FC",
        "9":"V.Gyokeres fc",
        "10":"KuiFutball",
        "11":"BetrayerFC",
        "12":"Gunners fc"
    },
    "player_name":{
        "0":"Zarif Zakwan",
        "1":"Muhamad Syahir Abu Bakar",
        "2":"Rasyid Razak",
        "3":"Mohd Shahzani Ali",
        "4":"Lantoi Bkc",
        "5":"Hafiz Ismail",
        "6":"Ike Singge",
        "7":"Master Finger",
        "8":"Laksamana Football Club",
        "9":"ozool ismail",
        "10":"Kuwie Mans",
        "11":"Han Takiya",
        "12":"dukun zai"
    },
    "event_total":{
        "0":77,
        "1":59,
        "2":48,
        "3":45,
        "4":40,
        "5":38,
        "6":37,
        "7":36,
        "8":32,
        "9":27,
        "10":24,
        "11":20,
        "12":18
    }
}