{
    "rank":{
        "0":1,
        "1":2,
        "2":3,
        "3":4,
        "4":5,
        "5":6,
        "6":7,
        "7":8,
        "8":9,
        "9":10,
        "10":11,
        "11":12,
        "12":13
    },
    "entry_name":{
        "0":"LPT fighter",
        "1":"RojakkingFC",
        "2":"Laksamana FC",
        "3":"KuiFutball",
        "4":"Nippon Taqara",
        "5":"V.Gyokeres fc",
        "6":"BetrayerFC",
        "7":"Yakkyakkyeah",
        "8":"Cem Fc",
        "9":"Goyangdek",
        "10":"Boboiboy Gentar",
        "11":"bukanSalahku",
        "12":"Gunners fc"
    },
    "player_name":{
        "0":"Lantoi Bkc",
        "1":"Mohd Shahzani Ali",
        "2":"Laksamana Football Club",
        "3":"Kuwie Mans",
        "4":"Muhamad Syahir Abu Bakar",
        "5":"ozool ismail",
        "6":"Han Takiya",
        "7":"Ike Singge",
        "8":"Rasyid Razak",
        "9":"Master Finger",
        "10":"Hafiz Ismail",
        "11":"Zarif Zakwan",
        "12":"dukun zai"
    },
    "event_total":{
        "0":67,
        "1":67,
        "2":59,
        "3":59,
        "4":56,
        "5":55,
        "6":51,
        "7":48,
        "8":48,
        "9":48,
        "10":42,
        "11":38,
        "12":37
    }
}