{"rank":{"0":1,"1":2,"2":3,"3":4,"4":5,"5":6,"6":7,"7":8,"8":9,"9":10,"10":11,"11":12,"12":13,"13":14,"14":15},"entry_name":{"0":"bukanSalahku","1":"BetrayerFC","2":"Yakkyakkyeah","3":"fighter","4":"artetateam","5":"Turudek","6":"RojakingFC","7":"Luncai mari","8":"beheng fc","9":"Nippon Taqara FC","10":"DukuLangsat FC","11":"Laksamama FC","12":"Rampage 04","13":"kuwi FT","14":"Fadhli-92"},"player_name":{"0":"Zarif Zakwan","1":"Han Takiya","2":"Ike Singge","3":"Lantoi Bkc","4":"ozool ismail","5":"Master Finger","6":"Mohd Shahzani Ali","7":"Rasyid Razak","8":"dukun zai","9":"Muhamad Syahir Abu Bakar","10":"Hafiz Ismail","11":"Laksamana Football Club","12":"Rampage Ozil","13":"Kuwie Mans","14":"MUHD FADHLI JAYA"},"total":{"0":1988,"1":1921,"2":1875,"3":1869,"4":1839,"5":1836,"6":1822,"7":1794,"8":1794,"9":1786,"10":1785,"11":1780,"12":1764,"13":1669,"14":1325}}